vaknl_NBC/__init__.py
vaknl_user/__init__.py
vaknl_user/event/__init__.py
vaknl_user/event/event.py
vaknl_user/event/filter.py
vaknl_user/event/other.py
vaknl_user/event/pageview.py
vaknl_user/event/reservation.py
vaknl_user/event/utils.py
vaknl_user/user/__init__.py
vaknl_user/user/email.py
vaknl_user/user/statistics.py
vaknl_user/user/user.py
vaknl_user/user/utils.py
vaknl_user-2.1.3.dist-info/LICENSE
vaknl_user-2.1.3.dist-info/METADATA
vaknl_user-2.1.3.dist-info/WHEEL
vaknl_user-2.1.3.dist-info/top_level.txt
vaknl_user-2.1.3.dist-info/RECORD
