Metadata-Version: 2.1
Name: vaknl-user
Version: 2.1.3
Summary: User class that defines a user based on clickstream data.
Home-page: https://github.com/vakantiesnl/vaknl-PyPi.git
Author: Merijn van Es
Author-email: merijn.vanes@vakanties.nl
License: UNKNOWN
Keywords: vaknl,pip
Platform: UNKNOWN
Requires-Python: >=3.7
Requires-Dist: google-auth (==1.18.0)
Requires-Dist: google-cloud-firestore (==1.8.1)
Requires-Dist: typing-extensions (==3.7.4.2)
Requires-Dist: dacite (==1.5.1)
